reapit_cdk/cloudfront_invalidation/__init__.py
reapit_cdk/cloudfront_invalidation/py.typed
reapit_cdk/cloudfront_invalidation/_jsii/__init__.py
reapit_cdk/cloudfront_invalidation/_jsii/cloudfront-invalidation@0.1.2.jsii.tgz
reapit_cdk.cloudfront_invalidation-0.1.2.dist-info/LICENSE
reapit_cdk.cloudfront_invalidation-0.1.2.dist-info/METADATA
reapit_cdk.cloudfront_invalidation-0.1.2.dist-info/WHEEL
reapit_cdk.cloudfront_invalidation-0.1.2.dist-info/top_level.txt
reapit_cdk.cloudfront_invalidation-0.1.2.dist-info/RECORD
